setup.py
extrom/__init__.py
extrom/extrom.py
extrom.egg-info/PKG-INFO
extrom.egg-info/SOURCES.txt
extrom.egg-info/dependency_links.txt
extrom.egg-info/entry_points.txt
extrom.egg-info/requires.txt
extrom.egg-info/top_level.txt
extrom/gdromlib/__init__.py
extrom/gdromlib/gdromlib.py