Metadata-Version: 1.1
Name: extrom
Version: 0.1.2
Summary: ROM Extraction tool from archived ROM set file
Home-page: https://github.com/masushin/extrom
Author: masushin
Author-email: shinsuke.masuda@gmail.com
License: MIT
Keywords: rom extract tool
Platform: UNKNOWN
Classifier: Development Status :: 3 - Alpha
Classifier: Intended Audience :: Other Audience
Classifier: Topic :: Games/Entertainment
Classifier: License :: OSI Approved :: MIT License
Classifier: Programming Language :: Python :: 3
Classifier: Programming Language :: Python :: 3.3
Classifier: Programming Language :: Python :: 3.4
Classifier: Programming Language :: Python :: 3.5
Classifier: Programming Language :: Python :: 3.6
